ubipop/__init__.py
ubipop/_matcher.py
ubipop/_utils.py
ubipop/cli.py
ubipop/ubi_manifest_client/__init__.py
ubipop/ubi_manifest_client/client.py
ubipop/ubi_manifest_client/models.py
ubi_population_tool-0.19.0.dist-info/LICENSE
ubi_population_tool-0.19.0.dist-info/METADATA
ubi_population_tool-0.19.0.dist-info/WHEEL
ubi_population_tool-0.19.0.dist-info/entry_points.txt
ubi_population_tool-0.19.0.dist-info/RECORD
