Metadata-Version: 2.3
Name: ubi-population-tool
Version: 0.19.0
Summary: Tool for populating ubi repositories
Home-page: https://github.com/release-engineering/ubi-population-tool
License: GPL-3.0-or-later
Requires-Python: >=3.8,<4.0
Classifier: Development Status :: 5 - Production/Stable
Classifier: Intended Audience :: Developers
Classifier: License :: OSI Approved :: GNU General Public License v3 or later (GPLv3+)
Classifier: Programming Language :: Python :: 3
Classifier: Programming Language :: Python :: 3.8
Classifier: Programming Language :: Python :: 3.9
Classifier: Programming Language :: Python :: 3.10
Classifier: Programming Language :: Python :: 3.11
Classifier: Programming Language :: Python :: 3.12
Classifier: Programming Language :: Python :: 3.13
Classifier: Topic :: Software Development :: Libraries :: Python Modules
Requires-Dist: attrs
Requires-Dist: fastpurge
Requires-Dist: more-executors
Requires-Dist: pubtools-pulplib
Requires-Dist: pyrsistent
Requires-Dist: requests-gssapi (>=1.3.0,<2.0.0)
Requires-Dist: requires
Requires-Dist: ubi-config
Requires-Dist: urllib3
Project-URL: Documentation, https://release-engineering.github.io/ubi-population-tool
Project-URL: Repository, https://github.com/release-engineering/ubi-population-tool
